usecase_registry/__about__.py
usecase_registry/__init__.py
usecase_registry/command.py
usecase_registry/errors.py
usecase_registry/py.typed
usecase_registry/registry.py
usecase_registry/usecase.py
usecase_registry-1.2.1.dist-info/METADATA
usecase_registry-1.2.1.dist-info/WHEEL
usecase_registry-1.2.1.dist-info/licenses/LICENSE.txt
usecase_registry-1.2.1.dist-info/RECORD
